{"traceID": "8602cf35a37d954a41e67553093b25ab", "spans": [{"traceID": "8602cf35a37d954a41e67553093b25ab", "spanID": "41e67553093b25ab", "operationName": "productpage.default.svc.cluster.local:9080/productpage", "references": [], "startTime": 1610646841273063, "duration": 68873, "tags": [{"key": "downstream_cluster", "type": "string", "value": "-"}, {"key": "response_size", "type": "string", "value": "5183"}, {"key": "user_agent", "type": "string", "value": "python-requests/2.25.1"}, {"key": "node_id", "type": "string", "value": "router~10.1.0.90~istio-ingressgateway-75f6d79f48-z8ngl.istio-system~istio-system.svc.cluster.local"}, {"key": "http.status_code", "type": "string", "value": "200"}, {"key": "http.url", "type": "string", "value": "http://localhost/productpage"}, {"key": "http.method", "type": "string", "value": "GET"}, {"key": "upstream_cluster", "type": "string", "value": "outbound|9080||productpage.default.svc.cluster.local"}, {"key": "guid:x-request-id", "type": "string", "value": "03d7414f-0405-9ce3-9c75-d06c5e47f8a4"}, {"key": "http.protocol", "type": "string", "value": "HTTP/1.1"}, {"key": "component", "type": "string", "value": "proxy"}, {"key": "response_flags", "type": "string", "value": "-"}, {"key": "request_size", "type": "string", "value": "0"}, {"key": "peer.address", "type": "string", "value": "192.168.65.3"}, {"key": "span.kind", "type": "string", "value": "client"}, {"key": "internal.span.format", "type": "string", "value": "zipkin"}], "logs": [], "processID": "p1", "warnings": null}, {"traceID": "8602cf35a37d954a41e67553093b25ab", "spanID": "fece7615501b9448", "operationName": "productpage.default.svc.cluster.local:9080/productpage", "references": [{"refType": "CHILD_OF", "traceID": "8602cf35a37d954a41e67553093b25ab", "spanID": "41e67553093b25ab"}], "startTime": 1610646841273910, "duration": 66950, "tags": [{"key": "user_agent", "type": "string", "value": "python-requests/2.25.1"}, {"key": "guid:x-request-id", "type": "string", "value": "03d7414f-0405-9ce3-9c75-d06c5e47f8a4"}, {"key": "upstream_cluster", "type": "string", "value": "inbound|9080||"}, {"key": "http.status_code", "type": "string", "value": "200"}, {"key": "http.protocol", "type": "string", "value": "HTTP/1.1"}, {"key": "component", "type": "string", "value": "proxy"}, {"key": "http.url", "type": "string", "value": "http://localhost/productpage"}, {"key": "response_flags", "type": "string", "value": "-"}, {"key": "response_size", "type": "string", "value": "5183"}, {"key": "node_id", "type": "string", "value": "sidecar~10.1.0.97~productpage-v1-65576bb7bf-bp6c7.default~default.svc.cluster.local"}, {"key": "peer.address", "type": "string", "value": "10.1.0.90"}, {"key": "http.method", "type": "string", "value": "GET"}, {"key": "downstream_cluster", "type": "string", "value": "-"}, {"key": "request_size", "type": "string", "value": "0"}, {"key": "span.kind", "type": "string", "value": "server"}, {"key": "internal.span.format", "type": "string", "value": "zipkin"}], "logs": [], "processID": "p2", "warnings": null}, {"traceID": "8602cf35a37d954a41e67553093b25ab", "spanID": "cc63189870399e09", "operationName": "details.default.svc.cluster.local:9080/*", "references": [{"refType": "CHILD_OF", "traceID": "8602cf35a37d954a41e67553093b25ab", "spanID": "fece7615501b9448"}], "startTime": 1610646841278679, "duration": 44756, "tags": [{"key": "http.method", "type": "string", "value": "GET"}, {"key": "http.status_code", "type": "string", "value": "200"}, {"key": "http.protocol", "type": "string", "value": "HTTP/1.1"}, {"key": "node_id", "type": "string", "value": "sidecar~10.1.0.97~productpage-v1-65576bb7bf-bp6c7.default~default.svc.cluster.local"}, {"key": "peer.address", "type": "string", "value": "10.1.0.97"}, {"key": "guid:x-request-id", "type": "string", "value": "03d7414f-0405-9ce3-9c75-d06c5e47f8a4"}, {"key": "component", "type": "string", "value": "proxy"}, {"key": "user_agent", "type": "string", "value": "python-requests/2.25.1"}, {"key": "response_size", "type": "string", "value": "178"}, {"key": "upstream_cluster", "type": "string", "value": "outbound|9080||details.default.svc.cluster.local"}, {"key": "http.url", "type": "string", "value": "http://details:9080/details/0"}, {"key": "downstream_cluster", "type": "string", "value": "-"}, {"key": "request_size", "type": "string", "value": "0"}, {"key": "response_flags", "type": "string", "value": "-"}, {"key": "span.kind", "type": "string", "value": "client"}, {"key": "internal.span.format", "type": "string", "value": "zipkin"}], "logs": [], "processID": "p2", "warnings": null}, {"traceID": "8602cf35a37d954a41e67553093b25ab", "spanID": "7e428d9eff6ce3df", "operationName": "details.default.svc.cluster.local:9080/*", "references": [{"refType": "CHILD_OF", "traceID": "8602cf35a37d954a41e67553093b25ab", "spanID": "cc63189870399e09"}], "startTime": 1610646841279126, "duration": 43862, "tags": [{"key": "user_agent", "type": "string", "value": "python-requests/2.25.1"}, {"key": "peer.address", "type": "string", "value": "10.1.0.97"}, {"key": "http.status_code", "type": "string", "value": "200"}, {"key": "http.method", "type": "string", "value": "GET"}, {"key": "guid:x-request-id", "type": "string", "value": "03d7414f-0405-9ce3-9c75-d06c5e47f8a4"}, {"key": "http.url", "type": "string", "value": "http://details:9080/details/0"}, {"key": "downstream_cluster", "type": "string", "value": "-"}, {"key": "request_size", "type": "string", "value": "0"}, {"key": "response_flags", "type": "string", "value": "-"}, {"key": "upstream_cluster", "type": "string", "value": "inbound|9080||"}, {"key": "component", "type": "string", "value": "proxy"}, {"key": "response_size", "type": "string", "value": "178"}, {"key": "node_id", "type": "string", "value": "sidecar~10.1.0.91~details-v1-79c697d759-tnv75.default~default.svc.cluster.local"}, {"key": "http.protocol", "type": "string", "value": "HTTP/1.1"}, {"key": "span.kind", "type": "string", "value": "server"}, {"key": "internal.span.format", "type": "string", "value": "zipkin"}], "logs": [], "processID": "p3", "warnings": null}, {"traceID": "8602cf35a37d954a41e67553093b25ab", "spanID": "d42386f10787adc0", "operationName": "reviews.default.svc.cluster.local:9080/*", "references": [{"refType": "CHILD_OF", "traceID": "8602cf35a37d954a41e67553093b25ab", "spanID": "fece7615501b9448"}], "startTime": 1610646841327231, "duration": 9876, "tags": [{"key": "http.status_code", "type": "string", "value": "200"}, {"key": "upstream_cluster", "type": "string", "value": "outbound|9080||reviews.default.svc.cluster.local"}, {"key": "request_size", "type": "string", "value": "0"}, {"key": "node_id", "type": "string", "value": "sidecar~10.1.0.97~productpage-v1-65576bb7bf-bp6c7.default~default.svc.cluster.local"}, {"key": "http.url", "type": "string", "value": "http://reviews:9080/reviews/0"}, {"key": "response_flags", "type": "string", "value": "-"}, {"key": "response_size", "type": "string", "value": "379"}, {"key": "guid:x-request-id", "type": "string", "value": "03d7414f-0405-9ce3-9c75-d06c5e47f8a4"}, {"key": "http.protocol", "type": "string", "value": "HTTP/1.1"}, {"key": "component", "type": "string", "value": "proxy"}, {"key": "downstream_cluster", "type": "string", "value": "-"}, {"key": "peer.address", "type": "string", "value": "10.1.0.97"}, {"key": "http.method", "type": "string", "value": "GET"}, {"key": "user_agent", "type": "string", "value": "python-requests/2.25.1"}, {"key": "span.kind", "type": "string", "value": "client"}, {"key": "internal.span.format", "type": "string", "value": "zipkin"}], "logs": [], "processID": "p2", "warnings": null}, {"traceID": "8602cf35a37d954a41e67553093b25ab", "spanID": "e2a3da8fc217377a", "operationName": "reviews.default.svc.cluster.local:9080/*", "references": [{"refType": "CHILD_OF", "traceID": "8602cf35a37d954a41e67553093b25ab", "spanID": "d42386f10787adc0"}], "startTime": 1610646841327669, "duration": 8751, "tags": [{"key": "http.status_code", "type": "string", "value": "200"}, {"key": "guid:x-request-id", "type": "string", "value": "03d7414f-0405-9ce3-9c75-d06c5e47f8a4"}, {"key": "user_agent", "type": "string", "value": "python-requests/2.25.1"}, {"key": "request_size", "type": "string", "value": "0"}, {"key": "response_size", "type": "string", "value": "379"}, {"key": "upstream_cluster", "type": "string", "value": "inbound|9080||"}, {"key": "http.url", "type": "string", "value": "http://reviews:9080/reviews/0"}, {"key": "component", "type": "string", "value": "proxy"}, {"key": "downstream_cluster", "type": "string", "value": "-"}, {"key": "response_flags", "type": "string", "value": "-"}, {"key": "node_id", "type": "string", "value": "sidecar~10.1.0.95~reviews-v2-6c5bf657cf-mgxzf.default~default.svc.cluster.local"}, {"key": "peer.address", "type": "string", "value": "10.1.0.97"}, {"key": "http.method", "type": "string", "value": "GET"}, {"key": "http.protocol", "type": "string", "value": "HTTP/1.1"}, {"key": "span.kind", "type": "string", "value": "server"}, {"key": "internal.span.format", "type": "string", "value": "zipkin"}], "logs": [], "processID": "p4", "warnings": null}, {"traceID": "8602cf35a37d954a41e67553093b25ab", "spanID": "d4cb25546c9eec28", "operationName": "ratings.default.svc.cluster.local:9080/*", "references": [{"refType": "CHILD_OF", "traceID": "8602cf35a37d954a41e67553093b25ab", "spanID": "e2a3da8fc217377a"}], "startTime": 1610646841332311, "duration": 2119, "tags": [{"key": "component", "type": "string", "value": "proxy"}, {"key": "user_agent", "type": "string", "value": "python-requests/2.25.1"}, {"key": "response_flags", "type": "string", "value": "-"}, {"key": "http.url", "type": "string", "value": "http://ratings:9080/ratings/0"}, {"key": "downstream_cluster", "type": "string", "value": "-"}, {"key": "peer.address", "type": "string", "value": "10.1.0.95"}, {"key": "http.status_code", "type": "string", "value": "200"}, {"key": "upstream_cluster", "type": "string", "value": "outbound|9080||ratings.default.svc.cluster.local"}, {"key": "guid:x-request-id", "type": "string", "value": "03d7414f-0405-9ce3-9c75-d06c5e47f8a4"}, {"key": "http.method", "type": "string", "value": "GET"}, {"key": "request_size", "type": "string", "value": "0"}, {"key": "response_size", "type": "string", "value": "48"}, {"key": "node_id", "type": "string", "value": "sidecar~10.1.0.95~reviews-v2-6c5bf657cf-mgxzf.default~default.svc.cluster.local"}, {"key": "http.protocol", "type": "string", "value": "HTTP/1.1"}, {"key": "span.kind", "type": "string", "value": "client"}, {"key": "internal.span.format", "type": "string", "value": "zipkin"}], "logs": [], "processID": "p4", "warnings": null}, {"traceID": "8602cf35a37d954a41e67553093b25ab", "spanID": "7babb7b00e9950b4", "operationName": "ratings.default.svc.cluster.local:9080/*", "references": [{"refType": "CHILD_OF", "traceID": "8602cf35a37d954a41e67553093b25ab", "spanID": "d4cb25546c9eec28"}], "startTime": 1610646841332790, "duration": 1132, "tags": [{"key": "upstream_cluster", "type": "string", "value": "inbound|9080||"}, {"key": "user_agent", "type": "string", "value": "python-requests/2.25.1"}, {"key": "http.status_code", "type": "string", "value": "200"}, {"key": "guid:x-request-id", "type": "string", "value": "03d7414f-0405-9ce3-9c75-d06c5e47f8a4"}, {"key": "http.protocol", "type": "string", "value": "HTTP/1.1"}, {"key": "request_size", "type": "string", "value": "0"}, {"key": "node_id", "type": "string", "value": "sidecar~10.1.0.96~ratings-v1-7d99676f7f-mdt24.default~default.svc.cluster.local"}, {"key": "peer.address", "type": "string", "value": "10.1.0.95"}, {"key": "http.url", "type": "string", "value": "http://ratings:9080/ratings/0"}, {"key": "response_flags", "type": "string", "value": "-"}, {"key": "component", "type": "string", "value": "proxy"}, {"key": "downstream_cluster", "type": "string", "value": "-"}, {"key": "response_size", "type": "string", "value": "48"}, {"key": "http.method", "type": "string", "value": "GET"}, {"key": "span.kind", "type": "string", "value": "server"}, {"key": "internal.span.format", "type": "string", "value": "zipkin"}], "logs": [], "processID": "p5", "warnings": null}], "processes": {"p1": {"serviceName": "istio-ingressgateway", "tags": [{"key": "ip", "type": "string", "value": "10.1.0.90"}]}, "p2": {"serviceName": "productpage.default", "tags": [{"key": "ip", "type": "string", "value": "10.1.0.97"}]}, "p3": {"serviceName": "details.default", "tags": [{"key": "ip", "type": "string", "value": "10.1.0.91"}]}, "p4": {"serviceName": "reviews.default", "tags": [{"key": "ip", "type": "string", "value": "10.1.0.95"}]}, "p5": {"serviceName": "ratings.default", "tags": [{"key": "ip", "type": "string", "value": "10.1.0.96"}]}}, "warnings": null}